animutils/__init__.py
animutils/anim.py
animutils/drumsticks.py
animutils/midi.py
animutils-0.0.8.dist-info/LICENSE
animutils-0.0.8.dist-info/METADATA
animutils-0.0.8.dist-info/WHEEL
animutils-0.0.8.dist-info/top_level.txt
animutils-0.0.8.dist-info/RECORD
