Metadata-Version: 2.1
Name: animutils
Version: 0.0.8
Summary: Utilities for musical animations in Blender.
Home-page: https://github.com/HuangPatrick16777216/animutils
Author: 3D Musicode
Author-email: huangpatrick16777216@gmail.com
License: UNKNOWN
Platform: UNKNOWN
Classifier: Programming Language :: Python :: 3
Classifier: License :: OSI Approved :: GNU General Public License v2 or later (GPLv2+)
Classifier: Operating System :: OS Independent
Requires-Dist: mido
